{"$schema":"http://json-schema.org/draft-04/schema#","$ref":"#/definitions/S3Check","definitions":{"ConfigMapKeySelector":{"required":["key"],"properties":{"name":{"type":"string"},"key":{"type":"string"},"optional":{"type":"boolean"}},"additionalProperties":false,"type":"object"},"EnvVar":{"properties":{"name":{"type":"string"},"value":{"type":"string"},"valueFrom":{"$schema":"http://json-schema.org/draft-04/schema#","$ref":"#/definitions/EnvVarSource"}},"additionalProperties":false,"type":"object"},"EnvVarSource":{"properties":{"configMapKeyRef":{"$schema":"http://json-schema.org/draft-04/schema#","$ref":"#/definitions/ConfigMapKeySelector"},"secretKeyRef":{"$schema":"http://json-schema.org/draft-04/schema#","$ref":"#/definitions/SecretKeySelector"}},"additionalProperties":false,"type":"object"},"S3Check":{"required":["name"],"properties":{"description":{"type":"string"},"name":{"type":"string"},"icon":{"type":"string"},"labels":{"patternProperties":{".*":{"type":"string"}},"type":"object"},"connection":{"type":"string"},"accessKey":{"$schema":"http://json-schema.org/draft-04/schema#","$ref":"#/definitions/EnvVar"},"secretKey":{"$ref":"#/definitions/EnvVar"},"region":{"type":"string"},"endpoint":{"type":"string"},"skipTLSVerify":{"type":"boolean"},"objectPath":{"type":"string"},"usePathStyle":{"type":"boolean"},"bucketName":{"type":"string"}},"additionalProperties":false,"type":"object"},"SecretKeySelector":{"required":["key"],"properties":{"name":{"type":"string"},"key":{"type":"string"},"optional":{"type":"boolean"}},"additionalProperties":false,"type":"object"}}}